<?xml version='1.0' encoding='UTF-8'?>
<tv source-info-url="https://github.com/martindidriksen/kvf-epg" generator-info-name="KVF EPG Scraper">
  <channel id="kvf.fo">
    <display-name>KVF</display-name>
  </channel>
  <programme start="20260628232500 " stop="20260629170000 " channel="kvf.fo">
    <title>Veðrið</title>
  </programme>
  <programme start="20260629170000 " stop="20260629173000 " channel="kvf.fo">
    <title>MORSA 8:12</title>
    <sub-title>- føroysk barnarøð</sub-title>
    <desc>Í nýggju barnarøðini Morsa fer Elisabeth á Bakka at vísa ymiska hárseting. Og vit vísa nýggju bretsku barnarøðina Katie, sum BBC hevur gjørt. Vertur: Jákup Wardum. Upptøka: Bjørg Mohr Andersen. Klipt: Bjørg Mohr Andersen og Sólfríð Maria í Rók. Lagt til rættis: Elin á Rógvi.</desc>
  </programme>
  <programme start="20260629173000 " stop="20260629174700 " channel="kvf.fo">
    <title>Vinus og Vimús 2 - 2:8</title>
    <sub-title>- føroysk barnasending</sub-title>
  </programme>
  <programme start="20260629174700 " stop="20260629175300 " channel="kvf.fo">
    <title>Pingu</title>
  </programme>
  <programme start="20260629175300 " stop="20260629180000 " channel="kvf.fo">
    <title>Pingu</title>
  </programme>
  <programme start="20260629180000 " stop="20260629185500 " channel="kvf.fo">
    <title>Dagur og vika við 3-2</title>
  </programme>
  <programme start="20260629185500 " stop="20260629190000 " channel="kvf.fo">
    <title>Veðrið</title>
  </programme>
  <programme start="20260629190000 " stop="20260629191500 " channel="kvf.fo">
    <title>$elfie</title>
    <sub-title>- surf´s up, føroyskt skemt (1:4)</sub-title>
    <desc>Ávirkarin Pauli fer til Tjørnuvíkar at surfa og skapa content. Hann er í toppformi, men dagurin gongur ikki heilt sum ætlað.</desc>
  </programme>
  <programme start="20260629191500 " stop="20260629202000 " channel="kvf.fo">
    <title>Horvnir arvingar VII 3:5</title>
    <sub-title>- loyniferðafólk</sub-title>
    <desc>Ein danskur maður fer eina vandafulla siglingsferð, sum fær álvarsligar fylgjur. Ikki einans fyri hann sjálvan, men eisini eftirkomararnar. Harímillum son hansara, sum nú er deyður. Leitanin eftir arvingum hjá soninum leiða okkum til fleiri meginlond. Mette Frisk og Adam Jon Kronegh skjalavørður leita og royna eisini at fáa greiðu á, hví arvingarnir og tann deyði hava mist sambandið.</desc>
  </programme>
  <programme start="20260629202000 " stop="20260629223000 " channel="kvf.fo">
    <title>FIFA HM 2026: Týskland - Paraguai</title>
  </programme>
  <programme start="20260629223000 " stop="20260629230000 " channel="kvf.fo">
    <title>Dagur og vika við 3-2</title>
  </programme>
  <programme start="20260629230000 " stop="20260629232500 " channel="kvf.fo">
    <title>Dagur og vika</title>
    <sub-title>- við teksti</sub-title>
  </programme>
  <programme start="20260629232500 " stop="20260630170000 " channel="kvf.fo">
    <title>Veðrið</title>
  </programme>
  <programme start="20260630170000 " stop="20260630171900 " channel="kvf.fo">
    <title>Vinus og Vimús 2 - 2:8</title>
    <sub-title>- føroysk barnasending</sub-title>
  </programme>
  <programme start="20260630171900 " stop="20260630172500 " channel="kvf.fo">
    <title>Pingu</title>
  </programme>
  <programme start="20260630172500 " stop="20260630173000 " channel="kvf.fo">
    <title>Pingu</title>
  </programme>
  <programme start="20260630173000 " stop="20260630180000 " channel="kvf.fo">
    <title>Alt um djór</title>
    <sub-title>- barnarøð frá BBC við føroyskari talu</sub-title>
  </programme>
  <programme start="20260630180000 " stop="20260630182500 " channel="kvf.fo">
    <title>Dagur og vika</title>
  </programme>
  <programme start="20260630182500 " stop="20260630184000 " channel="kvf.fo">
    <title>Veðrið</title>
  </programme>
  <programme start="20260630184000 " stop="20260630192000 " channel="kvf.fo">
    <title>Gekkur</title>
  </programme>
  <programme start="20260630192000 " stop="20260630194000 " channel="kvf.fo">
    <title>Veðurlagsvónir 3:6</title>
    <sub-title>- svensk røð frá 2023</sub-title>
    <desc>Svenska veðurlagsávirkanin frá flogferðslu eigur líka nógv útlát sum øll persónbilaferðslan í Svøríki. Ber til at gera flogferðsluna veðurlags-smartari? Ella skulu vit flúgva minni? Í sendingini eru Jonas Åkerman granskari innan flutning og stjóri fyri burðarygd hjá SAS Ann-Sofie Hörlin. Programmleiðari: Camilla Kvartoft. 3. partur av 6. Broadcast Company	SVT</desc>
  </programme>
  <programme start="20260630194000 " stop="20260630195000 " channel="kvf.fo">
    <title>Loppumarknaðarprei 5:6</title>
    <sub-title>- svensk røð frá 2022</sub-title>
    <desc>Sofia Rågenklint finnur eina antik køliboks fyri spottprís á loppumarknaði í Stora Karby. Sofia investerar í glas frá Kosta Boda.</desc>
  </programme>
  <programme start="20260630195000 " stop="20260630205000 " channel="kvf.fo">
    <title>Ein villari verð 1:4</title>
    <sub-title>- svensk røð frá 2022</sub-title>
    <desc>Kunnu endurskapt frumneyt og bisonar steðga hóttanini móti biologiska margfeldinum, og skulu gotlandross kunna sleppast leys? Røðin vísir royndir at endurskapa vistskipanir, sum eru "koppaðar". Í fyrsta parti snýr tað seg um teir stóru plantuátararnar. Programmleiðari: Anders Lundin.</desc>
  </programme>
  <programme start="20260630205000 " stop="20260630215000 " channel="kvf.fo">
    <title>FIFA HM 2026: Frakland - Svøríki</title>
  </programme>
</tv>
